lego_workflows/__init__.py
lego_workflows/components.py
lego_workflows/py.typed
lego_workflows-1.0.0.dist-info/METADATA
lego_workflows-1.0.0.dist-info/WHEEL
lego_workflows-1.0.0.dist-info/licenses/LICENSE
lego_workflows-1.0.0.dist-info/RECORD
