Metadata-Version: 2.3
Name: lego-workflows
Version: 1.0.0
Project-URL: Documentation, https://github.com/Tomperez98/lego-workflows#readme
Project-URL: Issues, https://github.com/Tomperez98/lego-workflows/issues
Project-URL: Source, https://github.com/Tomperez98/lego-workflows
Author-email: Tomas Perez Alvarez <tomasperezalvarez@gmail.com>
License-File: LICENSE
Classifier: Programming Language :: Python :: Implementation :: CPython
Classifier: Programming Language :: Python :: Implementation :: PyPy
Requires-Python: >=3.10
Requires-Dist: result
Provides-Extra: dev
Requires-Dist: pyrgo<3; extra == 'dev'
Requires-Dist: pytest-asyncio; extra == 'dev'
Requires-Dist: pytest-cov; extra == 'dev'
Requires-Dist: types-toml; extra == 'dev'
